{
    "type": "FeatureCollection",
    "name": "ATP-Antipodean_Is_",
    "features": [
        {
            "type": "Feature",
            "properties": {
                "LEVEL3_COD": "ATP",
                "LEVEL3_NAM": "Antipodean Is."
            },
            "geometry": {
                "type": "MultiPolygon",
                "coordinates": [
                    [
                        [
                            [
                                169.185474,
                                -52.5769935
                            ],
                            [
                                169.221574,
                                -52.5669935
                            ],
                            [
                                169.230774,
                                -52.5635935
                            ],
                            [
                                169.237174,
                                -52.5582935
                            ],
                            [
                                169.239174,
                                -52.5502935
                            ],
                            [
                                169.238274,
                                -52.5421935
                            ],
                            [
                                169.234174,
                                -52.5357935
                            ],
                            [
                                169.216874,
                                -52.5282935
                            ],
                            [
                                169.209674,
                                -52.4857935
                            ],
                            [
                                169.209374,
                                -52.4657935
                            ],
                            [
                                169.211374,
                                -52.4621935
                            ],
                            [
                                169.213274,
                                -52.4541935
                            ],
                            [
                                169.210774,
                                -52.4469935
                            ],
                            [
                                169.205274,
                                -52.4413935
                            ],
                            [
                                169.174174,
                                -52.4432935
                            ],
                            [
                                169.163574,
                                -52.4457935
                            ],
                            [
                                169.005874,
                                -52.5010935
                            ],
                            [
                                169.000774,
                                -52.5071935
                            ],
                            [
                                168.998874,
                                -52.5152935
                            ],
                            [
                                169.001374,
                                -52.5224935
                            ],
                            [
                                169.007774,
                                -52.5360935
                            ],
                            [
                                169.017174,
                                -52.5480935
                            ],
                            [
                                169.028274,
                                -52.5591935
                            ],
                            [
                                169.112974,
                                -52.5741935
                            ],
                            [
                                169.124674,
                                -52.5760935
                            ],
                            [
                                169.161674,
                                -52.5780935
                            ],
                            [
                                169.185474,
                                -52.5769935
                            ]
                        ]
                    ],
                    [
                        [
                            [
                                166.096574,
                                -50.9230935
                            ],
                            [
                                166.166874,
                                -50.9030935
                            ],
                            [
                                166.212774,
                                -50.8916935
                            ],
                            [
                                166.220474,
                                -50.8874935
                            ],
                            [
                                166.215474,
                                -50.8816935
                            ],
                            [
                                166.194474,
                                -50.8760935
                            ],
                            [
                                166.107774,
                                -50.8555935
                            ],
                            [
                                165.931374,
                                -50.8521935
                            ],
                            [
                                165.923574,
                                -50.8563935
                            ],
                            [
                                165.930574,
                                -50.8694935
                            ],
                            [
                                165.935474,
                                -50.8752935
                            ],
                            [
                                165.973574,
                                -50.9052935
                            ],
                            [
                                166.005874,
                                -50.9113935
                            ],
                            [
                                166.086374,
                                -50.9235935
                            ],
                            [
                                166.096574,
                                -50.9230935
                            ]
                        ]
                    ],
                    [
                        [
                            [
                                165.995574,
                                -50.6035935
                            ],
                            [
                                166.001374,
                                -50.6010935
                            ],
                            [
                                166.003574,
                                -50.5949935
                            ],
                            [
                                165.991074,
                                -50.5935935
                            ],
                            [
                                165.980574,
                                -50.5955935
                            ],
                            [
                                165.971574,
                                -50.5988935
                            ],
                            [
                                165.969374,
                                -50.6049935
                            ],
                            [
                                165.979174,
                                -50.6082935
                            ],
                            [
                                165.995574,
                                -50.6035935
                            ]
                        ]
                    ],
                    [
                        [
                            [
                                166.250774,
                                -50.8269935
                            ],
                            [
                                166.250274,
                                -50.8188935
                            ],
                            [
                                166.229374,
                                -50.7541935
                            ],
                            [
                                166.171374,
                                -50.7232935
                            ],
                            [
                                166.141374,
                                -50.6980935
                            ],
                            [
                                166.198874,
                                -50.6282935
                            ],
                            [
                                166.242174,
                                -50.5993935
                            ],
                            [
                                166.291974,
                                -50.5682935
                            ],
                            [
                                166.281874,
                                -50.5549935
                            ],
                            [
                                166.223574,
                                -50.5293935
                            ],
                            [
                                166.199374,
                                -50.5271935
                            ],
                            [
                                166.187974,
                                -50.5269935
                            ],
                            [
                                166.133874,
                                -50.5260935
                            ],
                            [
                                166.123574,
                                -50.5280935
                            ],
                            [
                                166.108274,
                                -50.5366935
                            ],
                            [
                                166.104174,
                                -50.5455935
                            ],
                            [
                                166.109374,
                                -50.5510935
                            ],
                            [
                                166.116374,
                                -50.5641935
                            ],
                            [
                                166.118274,
                                -50.5716935
                            ],
                            [
                                166.117174,
                                -50.5805935
                            ],
                            [
                                166.091374,
                                -50.6621935
                            ],
                            [
                                166.087774,
                                -50.6691935
                            ],
                            [
                                166.057174,
                                -50.6957935
                            ],
                            [
                                166.044474,
                                -50.7060935
                            ],
                            [
                                166.035274,
                                -50.7093935
                            ],
                            [
                                166.012174,
                                -50.7116935
                            ],
                            [
                                166.001674,
                                -50.7138935
                            ],
                            [
                                165.983574,
                                -50.7202935
                            ],
                            [
                                165.907974,
                                -50.7627935
                            ],
                            [
                                165.901674,
                                -50.7680935
                            ],
                            [
                                165.896674,
                                -50.7741935
                            ],
                            [
                                165.886974,
                                -50.8043935
                            ],
                            [
                                165.887174,
                                -50.8127935
                            ],
                            [
                                165.890574,
                                -50.8446935
                            ],
                            [
                                165.895574,
                                -50.8505935
                            ],
                            [
                                166.000774,
                                -50.8474935
                            ],
                            [
                                166.011374,
                                -50.8452935
                            ],
                            [
                                166.018874,
                                -50.8410935
                            ],
                            [
                                166.024174,
                                -50.8349935
                            ],
                            [
                                166.154374,
                                -50.8388935
                            ],
                            [
                                166.201374,
                                -50.8555935
                            ],
                            [
                                166.212474,
                                -50.8580935
                            ],
                            [
                                166.225574,
                                -50.8577935
                            ],
                            [
                                166.234674,
                                -50.8544935
                            ],
                            [
                                166.241074,
                                -50.8491935
                            ],
                            [
                                166.246074,
                                -50.8430935
                            ],
                            [
                                166.249674,
                                -50.8360935
                            ],
                            [
                                166.250774,
                                -50.8269935
                            ]
                        ]
                    ],
                    [
                        [
                            [
                                166.321874,
                                -50.5069935
                            ],
                            [
                                166.331674,
                                -50.5036935
                            ],
                            [
                                166.331874,
                                -50.4946935
                            ],
                            [
                                166.317774,
                                -50.4938935
                            ],
                            [
                                166.285774,
                                -50.4996935
                            ],
                            [
                                166.284974,
                                -50.5052935
                            ],
                            [
                                166.309174,
                                -50.5071935
                            ],
                            [
                                166.321874,
                                -50.5069935
                            ]
                        ]
                    ],
                    [
                        [
                            [
                                178.816374,
                                -49.7238935
                            ],
                            [
                                178.823074,
                                -49.7191935
                            ],
                            [
                                178.826374,
                                -49.7124935
                            ],
                            [
                                178.833274,
                                -49.6694935
                            ],
                            [
                                178.835774,
                                -49.6646935
                            ],
                            [
                                178.837774,
                                -49.6571935
                            ],
                            [
                                178.841074,
                                -49.6335935
                            ],
                            [
                                178.838874,
                                -49.6255935
                            ],
                            [
                                178.832774,
                                -49.6202935
                            ],
                            [
                                178.814974,
                                -49.6135935
                            ],
                            [
                                178.802474,
                                -49.6149935
                            ],
                            [
                                178.778574,
                                -49.6271935
                            ],
                            [
                                178.757174,
                                -49.6405935
                            ],
                            [
                                178.750774,
                                -49.6455935
                            ],
                            [
                                178.739174,
                                -49.6560935
                            ],
                            [
                                178.727474,
                                -49.6666935
                            ],
                            [
                                178.717474,
                                -49.6777935
                            ],
                            [
                                178.715274,
                                -49.6852935
                            ],
                            [
                                178.717174,
                                -49.7035935
                            ],
                            [
                                178.719374,
                                -49.7116935
                            ],
                            [
                                178.726874,
                                -49.7157935
                            ],
                            [
                                178.736874,
                                -49.7180935
                            ],
                            [
                                178.805274,
                                -49.7260935
                            ],
                            [
                                178.816374,
                                -49.7238935
                            ]
                        ]
                    ],
                    [
                        [
                            [
                                179.076874,
                                -47.6805935
                            ],
                            [
                                179.080774,
                                -47.6785935
                            ],
                            [
                                179.082774,
                                -47.6710935
                            ],
                            [
                                179.078074,
                                -47.6649935
                            ],
                            [
                                179.069674,
                                -47.6616935
                            ],
                            [
                                179.060274,
                                -47.6649935
                            ],
                            [
                                179.052474,
                                -47.6688935
                            ],
                            [
                                179.049174,
                                -47.6755935
                            ],
                            [
                                179.051374,
                                -47.6835935
                            ],
                            [
                                179.061074,
                                -47.6857935
                            ],
                            [
                                179.076874,
                                -47.6805935
                            ]
                        ]
                    ]
                ]
            }
        }
    ]
}